comel/__init__.py
comel/constants.py
comel/widgets.py
comel/wrapper.py
comel/icons/branch-closed.png
comel/icons/branch-end.png
comel/icons/branch-more.png
comel/icons/branch-open.png
comel/icons/checked-disabled.png
comel/icons/checked.png
comel/icons/dark-branch-closed.png
comel/icons/dark-branch-end.png
comel/icons/dark-branch-more.png
comel/icons/dark-branch-open.png
comel/icons/dark-checked-disabled.png
comel/icons/dark-checked.png
comel/icons/dark-radio-off.png
comel/icons/dark-radio-on.png
comel/icons/dark-vline.png
comel/icons/radio-off.png
comel/icons/radio-on.png
comel/icons/splitter-horz-bg.png
comel/icons/splitter-horz.png
comel/icons/splitter-vert-bg.png
comel/icons/splitter-vert.png
comel/icons/vline.png
comel/themes/dark.qss
comel/themes/light.qss
comel-0.3.0.dist-info/LICENSE
comel-0.3.0.dist-info/METADATA
comel-0.3.0.dist-info/WHEEL
comel-0.3.0.dist-info/top_level.txt
comel-0.3.0.dist-info/RECORD
