Metadata-Version: 2.2
Name: Comel
Version: 0.3.0
Summary: Opinionated PySide6 Light/Dark Theme Toggler.
Author-email: Huey Yeng <huey.yeng.mmu@gmail.com>
Maintainer-email: Huey Yeng <huey.yeng.mmu@gmail.com>
License: MIT License
Project-URL: Homepage, https://github.com/hueyyeng/Comel
Project-URL: Bug Reports, https://github.com/hueyyeng/Comel/issues
Project-URL: Source, https://github.com/hueyyeng/Comel
Keywords: python,library,qt,widgets,development
Classifier: Intended Audience :: Developers
Classifier: Programming Language :: Python :: 3.11
Classifier: Programming Language :: Python :: 3.10
Classifier: Programming Language :: Python :: 3.9
Classifier: Programming Language :: Python :: 3.8
Classifier: Programming Language :: Python :: 3.7
Classifier: Operating System :: MacOS
Classifier: Operating System :: POSIX :: Linux
Classifier: Operating System :: Microsoft :: Windows :: Windows 10
Classifier: Operating System :: Microsoft :: Windows :: Windows 11
Requires-Python: >=3.7
License-File: LICENSE
Requires-Dist: qtpy
Requires-Dist: darkdetect
Requires-Dist: PySide6
